README.md
setup.py
network_stability/__init__.py
network_stability.egg-info/PKG-INFO
network_stability.egg-info/SOURCES.txt
network_stability.egg-info/dependency_links.txt
network_stability.egg-info/requires.txt
network_stability.egg-info/top_level.txt