Metadata-Version: 2.1
Name: network-stability
Version: 1.0.3
Summary: Network connectivity and speed test.
Home-page: https://github.com/matheusccouto/network-stability
Author: Matheus Couto
Author-email: matheusccouto@gmail.com
License: UNKNOWN
Keywords: NETWORK,STABILITY,TEST,SPEED,CONNECTION
Platform: UNKNOWN
Classifier: Programming Language :: Python :: 3
Classifier: License :: OSI Approved :: MIT License
Classifier: Operating System :: OS Independent
Requires-Python: >=3.6
